pysunspec2-1.3.2.data/scripts/suns.py
sunspec2/__init__.py
sunspec2/device.py
sunspec2/mb.py
sunspec2/mdef.py
sunspec2/smdx.py
sunspec2/spreadsheet.py
sunspec2/xlsx.py
sunspec2/file/__init__.py
sunspec2/file/client.py
sunspec2/modbus/__init__.py
sunspec2/modbus/client.py
sunspec2/modbus/modbus.py
sunspec2/models/json/Makefile
sunspec2/models/json/model_1.json
sunspec2/models/json/model_10.json
sunspec2/models/json/model_101.json
sunspec2/models/json/model_102.json
sunspec2/models/json/model_103.json
sunspec2/models/json/model_11.json
sunspec2/models/json/model_111.json
sunspec2/models/json/model_112.json
sunspec2/models/json/model_113.json
sunspec2/models/json/model_12.json
sunspec2/models/json/model_120.json
sunspec2/models/json/model_121.json
sunspec2/models/json/model_122.json
sunspec2/models/json/model_123.json
sunspec2/models/json/model_124.json
sunspec2/models/json/model_125.json
sunspec2/models/json/model_126.json
sunspec2/models/json/model_127.json
sunspec2/models/json/model_128.json
sunspec2/models/json/model_129.json
sunspec2/models/json/model_13.json
sunspec2/models/json/model_130.json
sunspec2/models/json/model_131.json
sunspec2/models/json/model_132.json
sunspec2/models/json/model_133.json
sunspec2/models/json/model_134.json
sunspec2/models/json/model_135.json
sunspec2/models/json/model_136.json
sunspec2/models/json/model_137.json
sunspec2/models/json/model_138.json
sunspec2/models/json/model_139.json
sunspec2/models/json/model_14.json
sunspec2/models/json/model_140.json
sunspec2/models/json/model_141.json
sunspec2/models/json/model_142.json
sunspec2/models/json/model_143.json
sunspec2/models/json/model_144.json
sunspec2/models/json/model_145.json
sunspec2/models/json/model_15.json
sunspec2/models/json/model_16.json
sunspec2/models/json/model_160.json
sunspec2/models/json/model_17.json
sunspec2/models/json/model_18.json
sunspec2/models/json/model_19.json
sunspec2/models/json/model_2.json
sunspec2/models/json/model_201.json
pysunspec2-1.3.2.dist-info/LICENSE
pysunspec2-1.3.2.dist-info/METADATA
pysunspec2-1.3.2.dist-info/WHEEL
pysunspec2-1.3.2.dist-info/top_level.txt
pysunspec2-1.3.2.dist-info/RECORD
